jaskaran_hello/__init__.py
jaskaran_hello/main.py
jaskaran_hello-0.1.dist-info/METADATA
jaskaran_hello-0.1.dist-info/WHEEL
jaskaran_hello-0.1.dist-info/top_level.txt
jaskaran_hello-0.1.dist-info/RECORD
