Metadata-Version: 2.1
Name: jaskaran_hello
Version: 0.1
Summary: plus devide
Author: jaskaran
Author-email: jaskaran.singh@clobz.com
Classifier: Programming Language :: Python :: 3.9
Classifier: License :: OSI Approved :: MIT License
Classifier: Operating System :: OS Independent
